input_tool/__init__.py
input_tool/common/__init__.py
input_tool/common/check_updates.py
input_tool/common/commands.py
input_tool/common/messages.py
input_tool/common/os_config.py
input_tool/common/parser/options.py
input_tool/common/parser/parser.py
input_tool/common/parser/specifications.py
input_tool/common/programs/__init__.py
input_tool/common/programs/checker.py
input_tool/common/programs/generator.py
input_tool/common/programs/program.py
input_tool/common/programs/solution.py
input_tool/common/programs/validator.py
input_tool/common/recipes.py
input_tool/common/task_history.py
input_tool/common/task_queue.py
input_tool/common/tools_common.py
input_tool/input_generator.py
input_tool/input_sample.py
input_tool/input_tester.py
input_tool/itool.py
input_tool-2.0.2.dist-info/LICENSE
input_tool-2.0.2.dist-info/METADATA
input_tool-2.0.2.dist-info/WHEEL
input_tool-2.0.2.dist-info/entry_points.txt
input_tool-2.0.2.dist-info/RECORD
