Metadata-Version: 2.1
Name: input-tool
Version: 2.0.2
Summary: Tool which simplifies creating and testing inputs for programming contests.
Home-page: https://github.com/fezjo/input-tool/
License: MIT
Keywords: benchmark,contests,competitive-programming,tool
Author: jablkoj (Ján Hozza)
Requires-Python: >=3.8,<4.0
Classifier: Environment :: Console
Classifier: License :: OSI Approved :: MIT License
Classifier: Operating System :: Unix
Classifier: Programming Language :: Python :: 3
Classifier: Programming Language :: Python :: 3.8
Classifier: Programming Language :: Python :: 3.9
Classifier: Programming Language :: Python :: 3.10
Classifier: Programming Language :: Python :: 3.11
Classifier: Programming Language :: Python :: 3.12
Classifier: Topic :: Software Development :: Testing
Classifier: Topic :: System :: Benchmark
Classifier: Typing :: Typed
Requires-Dist: argcomplete (>=3.2.2,<4.0.0)
Requires-Dist: pyyaml (>=6.0.1,<7.0.0)
Requires-Dist: requests (>=2.31.0,<3.0.0)
Requires-Dist: tqdm (>=4.66.2,<5.0.0)
Project-URL: Repository, https://github.com/fezjo/input-tool/
